{
  "compatibilities": [
    "EC2",
    "FARGATE",
    "MANAGED_INSTANCES"
  ],
  "containerDefinitions": [
    {
      "cpu": 786,
      "environment": [
        {
          "name": "POSTGRES_USER",
          "value": "ecs-fargate"
        },
        {
          "name": "CLOUDFARE_ACCOUNT_ID",
          "value": "#"
        },
        {
          "name": "CLOUDFARE_SECRET_ACCESS_KEY",
          "value": "#"
        },
        {
          "name": "CLOUDFARE_ACCESS_KEY_ID",
          "value": "#"
        },
        {
          "name": "CLOUDFARE_PUBLIC_URL",
          "value": "http://localhost"
        },
        {
          "name": "POSTGRES_PASSWORD",
          "value": "ecs-fargate"
        },
        {
          "name": "POSTGRES_PORT",
          "value": "5432"
        },
        {
          "name": "POSTGRES_DB",
          "value": "upload_widget_db"
        },
        {
          "name": "CLOUDFARE_BUCKET",
          "value": "#"
        }
      ],
      "environmentFiles": [],
      "essential": true,
      "image": "856180141906.dkr.ecr.us-east-2.amazonaws.com/pos-tech-developer/widget-server@sha256:35adf2048792888bc0ff35011a2a139a502f3d5a0e1629292bcf4b7950cba2d9",
      "logConfiguration": {
        "logDriver": "awslogs",
        "options": {
          "awslogs-group": "/ecs/pos-tech-developer-widget-server",
          "awslogs-create-group": "true",
          "awslogs-region": "us-east-2",
          "awslogs-stream-prefix": "ecs"
        },
        "secretOptions": []
      },
      "memory": 1024,
      "memoryReservation": 1024,
      "mountPoints": [],
      "name": "widget-server",
      "portMappings": [
        {
          "appProtocol": "http",
          "containerPort": 3333,
          "hostPort": 3333,
          "name": "port",
          "protocol": "tcp"
        }
      ],
      "systemControls": [],
      "ulimits": [],
      "volumesFrom": []
    }
  ],
  "cpu": "1024",
  "enableFaultInjection": false,
  "executionRoleArn": "arn:aws:iam::856180141906:role/ecsTaskExecutionRole",
  "family": "pos-tech-developer-widget-server",
  "memory": "2048",
  "networkMode": "awsvpc",
  "placementConstraints": [],
  "registeredAt": "2025-12-09T18:17:17.353Z",
  "registeredBy": "arn:aws:iam::856180141906:root",
  "requiresAttributes": [
    {
      "name": "com.amazonaws.ecs.capability.logging-driver.awslogs"
    },
    {
      "name": "ecs.capability.execution-role-awslogs"
    },
    {
      "name": "com.amazonaws.ecs.capability.ecr-auth"
    },
    {
      "name": "com.amazonaws.ecs.capability.docker-remote-api.1.19"
    },
    {
      "name": "com.amazonaws.ecs.capability.docker-remote-api.1.21"
    },
    {
      "name": "ecs.capability.execution-role-ecr-pull"
    },
    {
      "name": "com.amazonaws.ecs.capability.docker-remote-api.1.18"
    },
    {
      "name": "ecs.capability.task-eni"
    },
    {
      "name": "com.amazonaws.ecs.capability.docker-remote-api.1.29"
    }
  ],
  "requiresCompatibilities": [
    "FARGATE"
  ],
  "revision": 1,
  "runtimePlatform": {
    "cpuArchitecture": "X86_64",
    "operatingSystemFamily": "LINUX"
  },
  "status": "ACTIVE",
  "taskDefinitionArn": "arn:aws:ecs:us-east-2:856180141906:task-definition/pos-tech-developer-widget-server:1",
  "volumes": [],
  "tags": [
    {
      "key": "IAC",
      "value": "false"
    }
  ]
}